capella_model_explorer/__init__.py
capella_model_explorer/__main__.py
capella_model_explorer/app.py
capella_model_explorer/components.py
capella_model_explorer/constants.py
capella_model_explorer/core.py
capella_model_explorer/icons.py
capella_model_explorer/inline-dark-mode.js
capella_model_explorer/reports.py
capella_model_explorer/state.py
capella_model_explorer/table-of-contents.js
capella_model_explorer-0.3.9.dist-info/licenses/LICENSES/Apache-2.0.txt
capella_model_explorer-0.3.9.dist-info/licenses/LICENSES/CC0-1.0.txt
capella_model_explorer-0.3.9.dist-info/METADATA
capella_model_explorer-0.3.9.dist-info/WHEEL
capella_model_explorer-0.3.9.dist-info/entry_points.txt
capella_model_explorer-0.3.9.dist-info/top_level.txt
capella_model_explorer-0.3.9.dist-info/RECORD
