Metadata-Version: 2.4
Name: capella-model-explorer
Version: 0.3.9
Summary: A webapp for exploring Capella models
Author: DB InfraGO AG
License-Expression: Apache-2.0
Project-URL: Homepage, https://github.com/dbinfrago/capella-model-explorer
Project-URL: Documentation, https://dbinfrago.github.io/capella-model-explorer
Platform: any
Classifier: Development Status :: 1 - Planning
Classifier: Natural Language :: English
Classifier: Operating System :: OS Independent
Classifier: Programming Language :: Python :: 3 :: Only
Classifier: Programming Language :: Python :: 3.11
Classifier: Programming Language :: Python :: 3.12
Classifier: Programming Language :: Python :: 3.13
Classifier: Typing :: Typed
Requires-Python: <3.14,>=3.11
License-File: LICENSES/Apache-2.0.txt
License-File: LICENSES/CC0-1.0.txt
Requires-Dist: capellambse-context-diagrams>=0.7.23
Requires-Dist: capellambse>=0.7.12
Requires-Dist: click>=8.3.1
Requires-Dist: jinja2>=3.1.6
Requires-Dist: logfmter>=0.0.11
Requires-Dist: lxml>=6.0.2
Requires-Dist: prometheus-client>=0.23.1
Requires-Dist: python-fasthtml>=0.12.35
Requires-Dist: uvicorn>=0.38.0
Dynamic: license-file
